CHANGES.txt
MANIFEST.in
README.txt
setup.py
seqSieve/__init__.py
seqSieve/seqSieve
seqSieve.egg-info/PKG-INFO
seqSieve.egg-info/SOURCES.txt
seqSieve.egg-info/dependency_links.txt
seqSieve.egg-info/requires.txt
seqSieve.egg-info/top_level.txt