Metadata-Version: 1.1
Name: seqSieve
Version: 0.9.2
Summary: Remove outlier sequences from multiple sequence alignment
Home-page: https://pypi.python.org/pypi/seqSieve/
Author: Janina Mass
Author-email: janina.mass@hhu.de
License: GPLv3
Platform: UNKNOWN
Classifier: Programming Language :: Python :: 2.7
Classifier: Programming Language :: Python :: 3
Classifier: Topic :: Scientific/Engineering :: Bio-Informatics
